analyst_intern/__init__.py
analyst_intern/cli.py
analyst_intern/utils.py
analyst_intern-0.0.5.dist-info/METADATA
analyst_intern-0.0.5.dist-info/WHEEL
analyst_intern-0.0.5.dist-info/entry_points.txt
analyst_intern-0.0.5.dist-info/RECORD
