Metadata-Version: 2.3
Name: analyst-intern
Version: 0.0.5
Summary: An analyst intern in your terminal
Author: Andrew Han
Author-email: handrew11@gmail.com
Classifier: Programming Language :: Python :: 2
Classifier: Programming Language :: Python :: 2.7
Classifier: Programming Language :: Python :: 3
Classifier: Programming Language :: Python :: 3.4
Classifier: Programming Language :: Python :: 3.5
Classifier: Programming Language :: Python :: 3.6
Classifier: Programming Language :: Python :: 3.7
Classifier: Programming Language :: Python :: 3.8
Classifier: Programming Language :: Python :: 3.9
Classifier: Programming Language :: Python :: 3.10
Classifier: Programming Language :: Python :: 3.11
Classifier: Programming Language :: Python :: 3.12
Classifier: Programming Language :: Python :: 3.13
Requires-Dist: click
Requires-Dist: langchain-text-splitters
Requires-Dist: tqdm
Requires-Dist: wordcel (>=0.2.18)
